autoslug/__init__.py
autoslug/fields.py
autoslug/models.py
autoslug/settings.py
autoslug/utils.py
django_autoslug_iplweb-1.9.4.dist-info/METADATA
django_autoslug_iplweb-1.9.4.dist-info/RECORD
django_autoslug_iplweb-1.9.4.dist-info/WHEEL
django_autoslug_iplweb-1.9.4.dist-info/top_level.txt
