Metadata-Version: 2.1
Name: django-autoslug-iplweb
Version: 1.9.4
Summary: An automated slug field for Django.
Home-page: https://github.com/neithere/django-autoslug/
Author: Andy Mikhailenko
Author-email: neithere@gmail.com
License: GNU Lesser General Public License (LGPL), Version 3
Download-URL: https://github.com/neithere/django-autoslug/archive/master.zip
Keywords: django field slug auto unique transliteration i18n
Platform: UNKNOWN
Classifier: Development Status :: 5 - Production/Stable
Classifier: Environment :: Web Environment
Classifier: Framework :: Django
Classifier: Intended Audience :: Developers
Classifier: License :: OSI Approved :: GNU Library or Lesser General Public License (LGPL)
Classifier: Programming Language :: Python
Classifier: Programming Language :: Python :: 2
Classifier: Programming Language :: Python :: 2.7
Classifier: Programming Language :: Python :: 3
Classifier: Programming Language :: Python :: 3.5
Classifier: Programming Language :: Python :: 3.6
Classifier: Programming Language :: Python :: Implementation :: CPython
Classifier: Topic :: Software Development :: Libraries :: Python Modules
Classifier: Topic :: Text Processing :: General
Requires: python (>= 2.7)
Requires: django (>= 1.7.10)
Provides-Extra: cyrillic
Provides-Extra: translitcodec
